nonebot_plugin_mystere_patch/__init__.py
nonebot_plugin_mystere_patch-1.0.0a6.dist-info/METADATA
nonebot_plugin_mystere_patch-1.0.0a6.dist-info/WHEEL
nonebot_plugin_mystere_patch-1.0.0a6.dist-info/RECORD
