Metadata-Version: 2.1
Name: nonebot-plugin-mystere-patch
Version: 1.0.0a6
Summary: Patch plugin for NoneBot2 mystere support.
Home-page: https://github.com/OpenMystere/nonebot-plugin-mystere-patch
License: MIT
Author: Madray Haven
Author-email: sgpublic2002@gmail.com
Requires-Python: >=3.9,<4.0
Classifier: License :: OSI Approved :: MIT License
Classifier: Programming Language :: Python :: 3
Classifier: Programming Language :: Python :: 3.9
Classifier: Programming Language :: Python :: 3.10
Classifier: Programming Language :: Python :: 3.11
Classifier: Programming Language :: Python :: 3.12
Requires-Dist: nonebot-plugin-guild-patch (>=0.2.3,<0.3.0)
Project-URL: Repository, https://github.com/OpenMystere/nonebot-plugin-mystere-patch
